minisom_gpu/__init__.py
minisom_gpu/functions.py
minisom_gpu/som.py
minisom_gpu-0.2.0.dist-info/METADATA
minisom_gpu-0.2.0.dist-info/WHEEL
minisom_gpu-0.2.0.dist-info/licenses/LICENSE
minisom_gpu-0.2.0.dist-info/RECORD
