Metadata-Version: 2.1
Name: minisom-gpu
Version: 0.2.0
Summary: Minimalistic implementation of the Self Organizing Maps (SOM) employing GPU.
Project-URL: Homepage, https://github.com/rctorres/minisom
Project-URL: Bug Tracker, https://github.com/rctorres/minisom/issues
Author-email: Rodrigo Coura Torres <torres.rc@gmail.com>
License-File: LICENSE
Classifier: License :: OSI Approved :: MIT License
Classifier: Operating System :: OS Independent
Classifier: Programming Language :: Python :: 3
Requires-Python: >=3.7
